opensr_dataloaders/S2NAIP_v4.py
opensr_dataloaders/SEN2NAIP_final.py
opensr_dataloaders/__init__.py
opensr_dataloaders/coco_dataset.py
opensr_dataloaders/custom_sen2.py
opensr_dataloaders/dataset_selector.py
opensr_dataloaders/image_augmentations.py
opensr_dataloaders/linear_transform.py
opensr_dataloaders/linear_transforms.py
opensr_dataloaders/sen2_test.py
opensr_dataloaders-0.0.16.dist-info/LICENSE
opensr_dataloaders-0.0.16.dist-info/METADATA
opensr_dataloaders-0.0.16.dist-info/WHEEL
opensr_dataloaders-0.0.16.dist-info/top_level.txt
opensr_dataloaders-0.0.16.dist-info/RECORD
