Metadata-Version: 2.1
Name: opensr-dataloaders
Version: 0.0.16
Summary: TEMPORARY: internal tool for dataset loading and sharing
Home-page: https://isp.uv.es/opensr/
Author: Simon Donike, Cesar Aybar, Luis Gomez Chova, Freddie Kalaitzis
Author-email: accounts@donike.net
License: MIT
Project-URL: Source Code, https://github.com/ESAopenSR/opensr-dataloaders
License-File: LICENSE
Requires-Dist: numpy==1.23.5
Requires-Dist: einops==0.6.0
Requires-Dist: rasterio==1.3.6
Requires-Dist: tqdm==4.64.1
Requires-Dist: torch==1.13.1
Requires-Dist: scikit-image==0.19.3
Requires-Dist: pytorch-lightning==1.9.0
Requires-Dist: torchvision==0.14.1
Requires-Dist: pandas==2.2.1
